README.rst
pynames/__init__.py
pynames/base.py
pynames/exceptions.py
pynames/from_list_generator.py
pynames/from_tables_generator.py
pynames/generators/__init__.py
pynames/generators/elven.py
pynames/generators/fixtures/elven_dnd_names_tables.json
pynames/generators/fixtures/elven_warhammer_names_tables.json
pynames/generators/fixtures/goblin_names_tables.json
pynames/generators/fixtures/korean_names_list.json
pynames/generators/fixtures/mongolian_names_list.json
pynames/generators/fixtures/orc_names_list.json
pynames/generators/fixtures/pagan_names_list.json
pynames/generators/fixtures/scandinavian_names_list.json
pynames/generators/goblin.py
pynames/generators/iron_kingdoms/__init__.py
pynames/generators/iron_kingdoms/fixtures/IK_caspian_midlunder_sulese_names_tables.csv
pynames/generators/iron_kingdoms/fixtures/IK_dwarf_names_tables.csv
pynames/generators/iron_kingdoms/fixtures/IK_en_settings.csv
pynames/generators/iron_kingdoms/fixtures/IK_gobber_names_tables.csv
pynames/generators/iron_kingdoms/fixtures/IK_gobber_names_templates.csv
pynames/generators/iron_kingdoms/fixtures/IK_iossan_nyss_names_tables.csv
pynames/generators/iron_kingdoms/fixtures/IK_khadoran_names_tables.csv
pynames/generators/iron_kingdoms/fixtures/IK_khadoran_templates.csv
pynames/generators/iron_kingdoms/fixtures/IK_ogrun_names_tables.csv
pynames/generators/iron_kingdoms/fixtures/IK_ryn_names_tables.csv
pynames/generators/iron_kingdoms/fixtures/IK_simple_fullname.csv
pynames/generators/iron_kingdoms/fixtures/IK_thurian_morridane_names_tables.csv
pynames/generators/iron_kingdoms/fixtures/IK_tordoran_names_tables.csv
pynames/generators/iron_kingdoms/fixtures/IK_trollkin_names_tables.csv
pynames/generators/iron_kingdoms/fixtures/README.rst
pynames/generators/korean.py
pynames/generators/mongolian.py
pynames/generators/orc.py
pynames/generators/russian.py
pynames/generators/scandinavian.py
pynames/names.py
pynames/relations.py
pynames/tests/__init__.py
pynames-0.2.4.dist-info/LICENSE
pynames-0.2.4.dist-info/WHEEL
pynames-0.2.4.dist-info/METADATA
pynames-0.2.4.dist-info/RECORD
