Metadata-Version: 2.1
Name: pynames
Version: 0.2.4
Summary: Name generation library.
Home-page: https://github.com/Tiendil/pynames
License: BSD-3
Keywords: gamedev,game,game development,names,procedural content generation
Author: Aliaksei Yaletski (Tiendil)
Author-email: a.eletsky@gmail.com
Requires-Python: >=3.6,<4.0
Classifier: Development Status :: 5 - Production/Stable
Classifier: Intended Audience :: Developers
Classifier: License :: OSI Approved :: BSD License
Classifier: License :: Other/Proprietary License
Classifier: Natural Language :: English
Classifier: Natural Language :: Russian
Classifier: Programming Language :: Python :: 3
Classifier: Programming Language :: Python :: 3.10
Classifier: Programming Language :: Python :: 3.6
Classifier: Programming Language :: Python :: 3.7
Classifier: Programming Language :: Python :: 3.8
Classifier: Programming Language :: Python :: 3.9
Classifier: Topic :: Games/Entertainment
Classifier: Topic :: Software Development :: Libraries :: Python Modules
Requires-Dist: unicodecsv (>=0.14,<0.15)
Project-URL: Repository, https://github.com/Tiendil/pynames
